qmaze_cipher/__init__.py
qmaze_cipher/core.py
qmaze_cipher-1.0.0.dist-info/licenses/LICENSE
qmaze_cipher-1.0.0.dist-info/METADATA
qmaze_cipher-1.0.0.dist-info/WHEEL
qmaze_cipher-1.0.0.dist-info/top_level.txt
qmaze_cipher-1.0.0.dist-info/RECORD
