Metadata-Version: 2.4
Name: qmaze_cipher
Version: 1.0.0
Summary: Quantum-resistant chaos-based encryption algorithm
Home-page: https://github.com/SanjiCo/qmaze_cipher
Author: [SanjiCo]
Author-email: [i.ckl53@outlook.com]
Classifier: Programming Language :: Python :: 3
Classifier: License :: OSI Approved :: MIT License
Classifier: Operating System :: OS Independent
Requires-Python: >=3.7
License-File: LICENSE
Dynamic: author
Dynamic: author-email
Dynamic: classifier
Dynamic: description
Dynamic: description-content-type
Dynamic: home-page
Dynamic: license-file
Dynamic: requires-python
Dynamic: summary
